RPPythonModules-0.0.3.dist-info/DESCRIPTION.rst
RPPythonModules-0.0.3.dist-info/METADATA
RPPythonModules-0.0.3.dist-info/RECORD
RPPythonModules-0.0.3.dist-info/WHEEL
RPPythonModules-0.0.3.dist-info/metadata.json
RPPythonModules-0.0.3.dist-info/top_level.txt
automationassets/__init__.py
automationassets/automationassets.py
azureforpython/__init__.py
azureforpython/azureforpython.py
launchdarklyforpython/__init__.py
launchdarklyforpython/launchdarklyforpython.py
