Metadata-Version: 2.0
Name: RPPythonModules
Version: 0.0.3
Summary: Package for Python Modules for Launch Darkly Automation
Home-page: UNKNOWN
Author: Livia Halim
Author-email: livia.halim@recordpoint.com
License: UNKNOWN
Platform: UNKNOWN
Classifier: Programming Language :: Python :: 2.7
Classifier: License :: OSI Approved :: MIT License
Classifier: Operating System :: OS Independent
Requires-Python: >=2.7
